MANIFEST.in
README.rst
setup.cfg
setup.py
ec2ssh/__init__.py
ec2ssh/ec2ssh.py
ec2ssh.egg-info/PKG-INFO
ec2ssh.egg-info/SOURCES.txt
ec2ssh.egg-info/dependency_links.txt
ec2ssh.egg-info/entry_points.txt
ec2ssh.egg-info/requires.txt
ec2ssh.egg-info/top_level.txt