Metadata-Version: 1.1
Name: ec2ssh
Version: 2.0.3
Summary: Manage all your connects to AWS ec2
Home-page: https://github.com/bjtox/ec2ssh-manager
Author: Antonio Bitonti
Author-email: antonio.bitonti@gmail.com
License: MIT
Keywords: aws ec2 ssh bastion_host
Platform: UNKNOWN
Classifier: Development Status :: 5 - Production/Stable
Classifier: License :: OSI Approved :: MIT License
Classifier: Programming Language :: Python :: 3
Classifier: Programming Language :: Python :: 3.3
Classifier: Programming Language :: Python :: 3.4
Classifier: Programming Language :: Python :: 3.5
